cloudflare_kv/__init__.py
cloudflare_kv/kv.py
cloudlare_kv-1.0.2.dist-info/LICENSE
cloudlare_kv-1.0.2.dist-info/METADATA
cloudlare_kv-1.0.2.dist-info/WHEEL
cloudlare_kv-1.0.2.dist-info/top_level.txt
cloudlare_kv-1.0.2.dist-info/RECORD
