Metadata-Version: 2.1
Name: cloudlare-kv
Version: 1.0.2
Summary: A simple Python wrapper to Cloudflare KV
Home-page: https://github.com/dineshsonachalam/cloudflare-kv
Author: Dinesh Sonachalam
Author-email: dineshsonachalam@gmail.com
License: MIT
Keywords: cloudflare KV
Platform: UNKNOWN
Classifier: Programming Language :: Python :: 3
Classifier: License :: OSI Approved :: MIT License
Classifier: Operating System :: OS Independent
Requires-Python: >=3.1
Requires-Dist: requests (==2.25.1)
